{"data":[{"name":"安全","value":214},{"name":"熟悉","value":205},{"name":"工作","value":200},{"name":"相关","value":188},{"name":"经验","value":186},{"name":"能力","value":176},{"name":"负责","value":173},{"name":"网络","value":165},{"name":"技术","value":163},{"name":"网络安全","value":158},{"name":"要求","value":138},{"name":"系统","value":132},{"name":"漏洞","value":121},{"name":"分析","value":120},{"name":"产品","value":119},{"name":"优先","value":118},{"name":"公司","value":118},{"name":"任职","value":112},{"name":"进行","value":103},{"name":"良好","value":102},{"name":"具有","value":101},{"name":"学历","value":101},{"name":"专业","value":100},{"name":"具备","value":93},{"name":"沟通","value":93},{"name":"测试","value":89},{"name":"原理","value":86},{"name":"计算机","value":86},{"name":"信息安全","value":85},{"name":"本科","value":85},{"name":"团队","value":84},{"name":"了解","value":81},{"name":"管理","value":81},{"name":"渗透","value":80},{"name":"防火墙","value":80},{"name":"岗位","value":79},{"name":"工具","value":77},{"name":"较强","value":74},{"name":"检测","value":73},{"name":"攻击","value":71},{"name":"事件","value":70},{"name":"常见","value":69},{"name":"掌握","value":68},{"name":"主流","value":66},{"name":"使用","value":66},{"name":"熟练","value":66},{"name":"能够","value":65},{"name":"开发","value":64},{"name":"维护","value":64},{"name":"配置","value":63},{"name":"项目","value":63},{"name":"实施","value":62},{"name":"协议","value":59},{"name":"设备","value":58},{"name":"攻防","value":57},{"name":"精通","value":57},{"name":"应用","value":56},{"name":"语言","value":55},{"name":"方法","value":54},{"name":"服务","value":54}]}